homebrew_python/__init__.py
homebrew_python/cli.py
homebrew_python/utils.py
homebrew_python-0.1.3.dist-info/entry_points.txt
homebrew_python-0.1.3.dist-info/LICENSE
homebrew_python-0.1.3.dist-info/WHEEL
homebrew_python-0.1.3.dist-info/METADATA
homebrew_python-0.1.3.dist-info/RECORD
