Metadata-Version: 2.1
Name: homebrew-python
Version: 0.1.3
Summary: 
Home-page: https://github.com/tddschn/homebrew-python
License: MIT
Keywords: homebrew,python
Author: Xinyuan Chen
Author-email: 45612704+tddschn@users.noreply.github.com
Requires-Python: >=3.10,<4.0
Classifier: License :: OSI Approved :: MIT License
Classifier: Programming Language :: Python :: 3
Classifier: Programming Language :: Python :: 3.10
Classifier: Topic :: Utilities
Requires-Dist: typer (>=0.4.1,<0.5.0)
Project-URL: Bug Tracker, https://github.com/tddschn/homebrew-python/issues
Project-URL: Repository, https://github.com/tddschn/homebrew-python
